{
	"name": "EibPC",
	"type": "light",
	"colors": {
		"editor.background": "#ffffff",
		"editor.foreground": "#000000"
	},
	"tokenColors": [
		{
			"settings": {
				"foreground": "#333333ff",
				"background": "#f5f5f5ff"
			}
		},
		{
			"name": "Comments",
			"scope": [
        "comment",
        "comment.line.epc",
				"punctuation.definition.comment"
			],
			"settings": {
				"fontStyle": "italic",
				"foreground": "#AAAAAA"
			}
		},
		{
			"name": "Comments: Preprocessor",
			"scope": "comment.block.preprocessor",
			"settings": {
				"fontStyle": "",
				"foreground": "#AAAAAA"
			}
		},
		{
			"name": "Comments: Documentation",
			"scope": [
				"comment.documentation",
				"comment.block.documentation"
			],
			"settings": {
				"foreground": "#448C27"
			}
		},
		{
			"name": "Macros",
			"scope": "macro",
			"settings": {
				"background": "#96000014",
				"foreground": "#660000"
			}
		},
		{
			"name": "Operators",
			"scope": "keyword.operator",
			"settings": {
				"foreground": "#777777"
			}
		},
		{
			"name": "Keywords",
			"scope": [
				"keyword",
				"storage"
			],
			"settings": {
				"foreground": "#0c4897"
			}
		},
		{
			"name": "Types",
			"scope": [
				"storage.type",
				"support.type"
			],
			"settings": {
				"foreground": "#7A3E9D"
			}
		},
		{
			"name": "Language Constants",
			"scope": [
				"constant.language",
				"support.constant",
				"variable.language"
			],
			"settings": {
				"foreground": "#AB6526"
			}
		},
		{
			"name": "Variables",
			"scope": [
				"variable",
				"support.variable"
			],
			"settings": {
				"foreground": "#7A3E9D"
			}
		},
		{
			"name": "Functions",
			"scope": [
				"entity.name.function",
				"support.function"
			],
			"settings": {
				"fontStyle": "bold",
				"foreground": "#AA3731"
			}
		},
		{
			"name": "Classes",
			"scope": [
				"entity.name.type",
				"entity.other.inherited-class",
				"support.class"
			],
			"settings": {
				"fontStyle": "bold",
				"foreground": "#7A3E9D"
			}
		},
		{
			"name": "Exceptions",
			"scope": "entity.name.exception",
			"settings": {
				"foreground": "#660000"
			}
		},
		{
			"name": "Sections",
			"scope": "entity.name.section",
			"settings": {
				"fontStyle": "bold"
			}
		},
		{
			"name": "Numbers, Characters",
			"scope": [
				"constant.numeric",
				"constant.character",
				"constant"
			],
			"settings": {
				"foreground": "#AB6526"
			}
		},
		{
			"name": "Strings",
			"scope": "string",
			"settings": {
				"foreground": "#448C27"
			}
		},
		{
			"name": "Group Adresses",
			"scope": "string.groupaddress.epc",
			"settings": {
				"foreground": "#4B83CD"
			}
		},
		{
			"name": "Global Sections",
			"scope": "section.epc",
			"settings": {
        "foreground": "#ff0000",
        "fontStyle": "italic bold"
			}
		},
		{
			"name": "Strings: Escape Sequences",
			"scope": "constant.character.escape",
			"settings": {
				"foreground": "#777777"
			}
		},
		{
			"name": "Strings: Symbols",
			"scope": "constant.other.symbol",
			"settings": {
				"foreground": "#AB6526"
			}
		},
		{
			"name": "Punctuation",
			"scope": "punctuation",
			"settings": {
				"foreground": "#777777"
			}
		},
		{
			"name": "Macros",
			"scope": [
				"macro.include",
				"macro.include.file"
			],
			"settings": {
        "foreground": "#ff0000",
				"background": "#EAEBE6"
			}
		}
	]
}